skip/__init__.py
skip/skip.py
skip_python-0.1.4.dist-info/LICENSE.txt
skip_python-0.1.4.dist-info/METADATA
skip_python-0.1.4.dist-info/WHEEL
skip_python-0.1.4.dist-info/top_level.txt
skip_python-0.1.4.dist-info/RECORD
