Metadata-Version: 2.1
Name: skip-python
Version: 0.1.4
Summary: A helper library to sign/send bundles and secure transactions to the Skip Relay in Python.
Home-page: http://packages.python.org/an_example_pypi_project
Author: Jeremy Liu
Author-email: Skip Protocol <jeremy@skip.money>
License: MIT
Project-URL: Homepage, https://github.com/skip-mev/skip-py
Classifier: Programming Language :: Python :: 3
Classifier: License :: OSI Approved :: MIT License
Classifier: Operating System :: OS Independent
Requires-Python: >=3.10
License-File: LICENSE.txt
Requires-Dist: setuptools (>=61.0)
Requires-Dist: cosmpy (>=0.6.0)
Requires-Dist: httpx (>=0.23.0)
